folder_organizer/__init__.py
folder_organizer/constants.py
folder_organizer/open.py
folder_organizer/organizer.py
folder_organizer/py_resources.py
folder_organizer/interfaces/__init__.py
folder_organizer/interfaces/folder_ui.py
folder_organizer/interfaces/mainwindow_ui.py
folder_organizer/interfaces/new_ui.py
folder_organizer/utils/__init__.py
folder_organizer/utils/organize.py
folder_organizer-1.3.data/data/folder-organizer-resources/data.json
folder_organizer-1.3.data/data/folder-organizer-resources/folder
folder_organizer-1.3.dist-info/LICENSE
folder_organizer-1.3.dist-info/METADATA
folder_organizer-1.3.dist-info/WHEEL
folder_organizer-1.3.dist-info/entry_points.txt
folder_organizer-1.3.dist-info/top_level.txt
folder_organizer-1.3.dist-info/RECORD
